<?xml version="1.0" encoding="UTF-8"?>
<objects serializationModel="Studio.02.02.00">
	<object class="AudioFile" id="{a040f66d-a9a5-4fb7-8604-1f394fca8530}">
		<property name="assetPath">
			<value>UI/UI_Hover_2.wav</value>
		</property>
		<property name="frequencyInKHz">
			<value>96</value>
		</property>
		<property name="channelCount">
			<value>2</value>
		</property>
		<property name="length">
			<value>0.5161458333333333</value>
		</property>
		<relationship name="masterAssetFolder">
			<destination>{24cbe21b-1d8a-48a9-9c4f-234a8fa8ded4}</destination>
		</relationship>
	</object>
</objects>
